logbasic/__init__.py
logbasic/color_code.py
logbasic/log_type_text.py
logbasic-0.0.9.dist-info/LICENSE
logbasic-0.0.9.dist-info/METADATA
logbasic-0.0.9.dist-info/WHEEL
logbasic-0.0.9.dist-info/top_level.txt
logbasic-0.0.9.dist-info/RECORD
